namlab_analysis/__init__.py
namlab_analysis/functions/__init__.py
namlab_analysis/functions/analysis.py
namlab_analysis/functions/behavior.py
namlab_analysis/functions/data_io.py
namlab_analysis/functions/general.py
namlab_analysis/functions/nwb.py
namlab_analysis/functions/photometry.py
namlab_analysis/functions/plot.py
namlab_analysis-0.1.2.dist-info/METADATA
namlab_analysis-0.1.2.dist-info/WHEEL
namlab_analysis-0.1.2.dist-info/top_level.txt
namlab_analysis-0.1.2.dist-info/RECORD
