Metadata-Version: 2.1
Name: namlab-analysis
Version: 0.1.2
Summary: analysis codes for namboodiri lab
Home-page: https://github.com/namboodirilab/namlab-analysis
Author: huijeong
Author-email: huijeong.jeong00@gmail.com
Keywords: namlab,namboodiri
